yeti/__init__.py
yeti/api.py
yeti/client.py
yeti/errors.py
yeti_python-2.1.1.dist-info/LICENSE
yeti_python-2.1.1.dist-info/METADATA
yeti_python-2.1.1.dist-info/WHEEL
yeti_python-2.1.1.dist-info/RECORD
